ai_firewall/__init__.py
ai_firewall/client.py
ai_firewall/exceptions.py
ai_firewall/models.py
ai_firewall-0.1.0.dist-info/METADATA
ai_firewall-0.1.0.dist-info/WHEEL
ai_firewall-0.1.0.dist-info/top_level.txt
ai_firewall-0.1.0.dist-info/RECORD
