Metadata-Version: 2.4
Name: ai-firewall
Version: 0.1.0
Summary: Python SDK for AI Agent Safety Filter - validate AI agent actions against policies
Author: AI Firewall Team
License: MIT
Project-URL: Homepage, https://github.com/yourusername/ai-firewall
Project-URL: Documentation, https://github.com/yourusername/ai-firewall#readme
Project-URL: Repository, https://github.com/yourusername/ai-firewall
Keywords: ai,agents,security,firewall,safety,llm,guardrails
Classifier: Development Status :: 3 - Alpha
Classifier: Intended Audience :: Developers
Classifier: License :: OSI Approved :: MIT License
Classifier: Programming Language :: Python :: 3
Classifier: Programming Language :: Python :: 3.10
Classifier: Programming Language :: Python :: 3.11
Classifier: Programming Language :: Python :: 3.12
Classifier: Programming Language :: Python :: 3.13
Classifier: Topic :: Security
Classifier: Topic :: Software Development :: Libraries :: Python Modules
Requires-Python: >=3.10
Requires-Dist: httpx>=0.25.0
Provides-Extra: dev
Requires-Dist: pytest>=7.0.0; extra == "dev"
Requires-Dist: pytest-asyncio>=0.21.0; extra == "dev"
